owasp_schema/__init__.py
owasp_schema/chapter.json
owasp_schema/committee.json
owasp_schema/common.json
owasp_schema/project.json
owasp_schema/utils/__init__.py
owasp_schema/utils/schema_validators.py
owasp_schema-0.1.51.dist-info/METADATA
owasp_schema-0.1.51.dist-info/WHEEL
owasp_schema-0.1.51.dist-info/licenses/LICENSE
owasp_schema-0.1.51.dist-info/RECORD
