Metadata-Version: 2.4
Name: owasp-schema
Version: 0.1.51
Summary: A collection of OWASP schemas
License: MIT
License-File: LICENSE
Keywords: owasp,schema,json-schema
Author: Arkadii Yakovets
Author-email: arkadii.yakovets@owasp.org
Requires-Python: >=3.13,<4.0
Classifier: Development Status :: 4 - Beta
Classifier: Intended Audience :: Developers
Classifier: License :: OSI Approved :: MIT License
Classifier: Programming Language :: Python :: 3
Classifier: Programming Language :: Python :: 3.13
Classifier: Programming Language :: Python :: 3.14
Classifier: Topic :: Software Development :: Libraries :: Python Modules
Requires-Dist: jsonschema (>=4.23.0,<5.0.0)
Requires-Dist: pyyaml (>=6.0.2,<7.0.0)
Requires-Dist: validators (>=0.35.0,<0.36.0)
Project-URL: Homepage, https://nest.owasp.org
Project-URL: Repository, https://github.com/OWASP/Nest
